mchammer/__init__.py
mchammer/_version.py
mchammer/_internal/__init__.py
mchammer/_internal/atom.py
mchammer/_internal/bond.py
mchammer/_internal/collapser.py
mchammer/_internal/mc_operations.py
mchammer/_internal/molecule.py
mchammer/_internal/optimizer.py
mchammer/_internal/radii.py
mchammer/_internal/results.py
mchammer/_internal/utilities.py
MCHammer-2024.2.29.0.dist-info/LICENSE
MCHammer-2024.2.29.0.dist-info/METADATA
MCHammer-2024.2.29.0.dist-info/WHEEL
MCHammer-2024.2.29.0.dist-info/top_level.txt
MCHammer-2024.2.29.0.dist-info/RECORD
